div_iq_library/__init__.py
div_iq_library/div_iq_library.py
div_iq_library-0.1.dist-info/METADATA
div_iq_library-0.1.dist-info/WHEEL
div_iq_library-0.1.dist-info/top_level.txt
div_iq_library-0.1.dist-info/RECORD
