Metadata-Version: 2.1
Name: div-iq-library
Version: 0.1
Summary: Good one
Author: Divyanshi
License: UNKNOWN
Platform: UNKNOWN
